lightonmuse/__init__.py
lightonmuse/api_requests.py
lightonmuse/client_side.py
lightonmuse/resources.py
lightonmuse-0.5.0.dist-info/LICENSE
lightonmuse-0.5.0.dist-info/METADATA
lightonmuse-0.5.0.dist-info/WHEEL
lightonmuse-0.5.0.dist-info/top_level.txt
lightonmuse-0.5.0.dist-info/RECORD
