Metadata-Version: 2.1
Name: lightonmuse
Version: 0.5.0
Summary: Python client for the LightOn Muse API
Home-page: https://github.com/lightonai/lightonmuse
Author: LightOn AI Research
Author-email: support@lighton.ai
License: UNKNOWN
Keywords: NLP,API,AI
Platform: UNKNOWN
Classifier: Programming Language :: Python
Classifier: Programming Language :: Python :: 3
Classifier: Programming Language :: Python :: 3.7
Classifier: Programming Language :: Python :: 3.8
Classifier: Programming Language :: Python :: 3.9
Classifier: Programming Language :: Python :: 3.10
Classifier: Topic :: Scientific/Engineering :: Artificial Intelligence
Classifier: Development Status :: 4 - Beta
Classifier: Intended Audience :: Science/Research
Classifier: License :: Other/Proprietary License
License-File: LICENSE
Requires-Dist: requests (>=2.26.0)
Requires-Dist: numpy (>=1.21.6)
